monufacture
