Metadata-Version: 1.0
Name: Monufacture
Version: 0.2.14
Summary: A lightweight factory framework for easily generating test data in MongoDB
Home-page: http://github.com/gamechanger/monufacture
Author: Tom Leach
Author-email: tom@gc.io
License: BSD
Keywords: mongo mongodb database testing factory pymongo
Platform: UNKNOWN
